main.py
huspm_ce-0.1.0.dist-info/METADATA
huspm_ce-0.1.0.dist-info/WHEEL
huspm_ce-0.1.0.dist-info/top_level.txt
huspm_ce-0.1.0.dist-info/RECORD
