Metadata-Version: 2.4
Name: huspm-ce
Version: 0.1.0
Summary: Add your description here
Requires-Python: >=3.13
Requires-Dist: typer>=0.20.0
